gsdl/__init__.py
gsdl/__main__.py
gsdl/fps_clock.py
gsdl/frame.py
gsdl/hellomsg.py
gsdl/image.py
gsdl/label.py
gsdl/rect.py
gsdl/simple_button.py
gsdl/utils.py
gsdl/win_button.py
gsdl-1.0.6.dist-info/LICENSE
gsdl-1.0.6.dist-info/METADATA
gsdl-1.0.6.dist-info/WHEEL
gsdl-1.0.6.dist-info/entry_points.txt
gsdl-1.0.6.dist-info/top_level.txt
gsdl-1.0.6.dist-info/RECORD
