Metadata-Version: 2.1
Name: gsdl
Version: 1.0.6
Summary: Pygame GUI Library.
Home-page: https://github.com/Pixelsuft/gsdl
Author: Pixelsuft
License: MIT
Project-URL: Readme, https://github.com/Pixelsuft/gsdl/blob/main/README.MD
Project-URL: Example, https://github.com/Pixelsuft/gsdl/blob/main/main.py
Project-URL: Issue tracker, https://github.com/Pixelsuft/gsdl/issues
Keywords: gsdl
Platform: UNKNOWN
Classifier: License :: OSI Approved :: MIT License
Classifier: Programming Language :: Python :: 3.6
Classifier: Programming Language :: Python :: 3.7
Classifier: Programming Language :: Python :: 3.8
Classifier: Programming Language :: Python :: 3.9
Requires-Python: >=3.6
License-File: LICENSE
Requires-Dist: pygame
Requires-Dist: Pillow
Requires-Dist: buildozer
